{"SkillPointsPerDay": 0, "SpellsKnown": [], "Will": ["+0", "+0", "+1", "+1", "+1", "+2", "+2", "+2", "+3", "+3", "+3", "+4", "+4", "+4", "+5", "+5", "+5", "+6", "+6", "+6"], "SpellsPerDay": {}, "BaseAttackBonus": ["+1", "+2", "+3", "+4", "+5", "+6/+1", "+7/+2", "+8/+3", "+9/+4", "+10/+5", "+11/+6/+1", "+12/+7/+2", "+13/+8/+3", "+14/+9/+4", "+15/+10/+5", "+16/+11/+6/+1", "+17/+12/+7/+2", "+18/+13/+8/+3", "+19/+14/+9/+4", "+20/+15/+10/+5"], "Name": "shifter+cavalier", "HitDice": [], "Reflex": ["+2", "+3", "+3", "+4", "+4", "+5", "+5", "+6", "+6", "+7", "+7", "+8", "+8", "+9", "+9", "+10", "+10", "+11", "+11", "+12"], "Fortitude": ["+2", "+3", "+3", "+4", "+4", "+5", "+5", "+6", "+6", "+7", "+7", "+8", "+8", "+9", "+9", "+10", "+10", "+11", "+11", "+12"], "SpecialAbilities": ["Shifter aspect, shifter claws, wild empathy + Challenge 1/day, mount, order, tactician", "Defensive instinct, track + Order ability", "Shifter claws increase, woodland stride + Cavalier\u2019s charge", "Defensive instinct (+1), wild shape (1/day) + Challenge 2/day, expert trainer", "Second aspect, trackless step + Banner", "Wild shape (2/day) + Bonus feat", "Shifter claws increase + Challenge 3/day", "Defensive instinct (+2), wild shape (3/day) + Order ability", "Chimeric aspect + Greater tactician", "Third aspect, wild shape (4/day) + Challenge 4/day", "Shifter claws increase + Mighty charge", "Defensive instinct (+3), wild shape (5/day) + Bonus feat, demanding challenge", "Shifter claws increase + Challenge 5/day", "Greater chimeric aspect, wild shape (6/day) + Greater banner", "Fourth aspect + Order ability", "Defensive instinct (+4), wild shape (7/day) + Challenge 6/day", "Shifter claws increase + Master tactician", "Wild shape (8/day) + Bonus feat", "Shifter claws increase + Challenge 7/day", "Defensive instinct (+5), final aspect + Supreme charge"]}