{"SkillPointsPerDay": 0, "SpellsKnown": [], "Will": ["+2", "+3", "+3", "+4", "+4", "+5", "+5", "+6", "+6", "+7", "+7", "+8", "+8", "+9", "+9", "+10", "+10", "+11", "+11", "+12"], "SpellsPerDay": {"summoner": [["1", "\u2014", "\u2014", "\u2014", "\u2014", "\u2014"], ["2", "\u2014", "\u2014", "\u2014", "\u2014", "\u2014"], ["3", "\u2014", "\u2014", "\u2014", "\u2014", "\u2014"], ["3", "1", "\u2014", "\u2014", "\u2014", "\u2014"], ["4", "2", "\u2014", "\u2014", "\u2014", "\u2014"], ["4", "3", "\u2014", "\u2014", "\u2014", "\u2014"], ["4", "3", "1", "\u2014", "\u2014", "\u2014"], ["4", "4", "2", "\u2014", "\u2014", "\u2014"], ["5", "4", "3", "\u2014", "\u2014", "\u2014"], ["5", "4", "3", "1", "\u2014", "\u2014"], ["5", "4", "4", "2", "\u2014", "\u2014"], ["5", "5", "4", "3", "\u2014", "\u2014"], ["5", "5", "4", "3", "1", "\u2014"], ["5", "5", "4", "4", "2", "\u2014"], ["5", "5", "5", "4", "3", "\u2014"], ["5", "5", "5", "4", "3", "1"], ["5", "5", "5", "4", "4", "2"], ["5", "5", "5", "5", "4", "3"], ["5", "5", "5", "5", "5", "4"], ["5", "5", "5", "5", "5", "5"]]}, "BaseAttackBonus": ["+1", "+2", "+3", "+4", "+5", "+6/+1", "+7/+2", "+8/+3", "+9/+4", "+10/+5", "+11/+6/+1", "+12/+7/+2", "+13/+8/+3", "+14/+9/+4", "+15/+10/+5", "+16/+11/+6/+1", "+17/+12/+7/+2", "+18/+13/+8/+3", "+19/+14/+9/+4", "+20/+15/+10/+5"], "Name": "summoner+shifter", "HitDice": [], "Reflex": ["+2", "+3", "+3", "+4", "+4", "+5", "+5", "+6", "+6", "+7", "+7", "+8", "+8", "+9", "+9", "+10", "+10", "+11", "+11", "+12"], "Fortitude": ["+2", "+3", "+3", "+4", "+4", "+5", "+5", "+6", "+6", "+7", "+7", "+8", "+8", "+9", "+9", "+10", "+10", "+11", "+11", "+12"], "SpecialAbilities": ["Cantrips, Eidolon, Life link, Summon monster I + Shifter aspect, shifter claws, wild empathy", "Bond senses + Defensive instinct, track", "Summon monster II + Shifter claws increase, woodland stride", "Shield ally + Defensive instinct (+1), wild shape (1/day)", "Summon monster III + Second aspect, trackless step", "Maker\u2019s call + Wild shape (2/day)", "Summon monster IV + Shifter claws increase", "Transposition + Defensive instinct (+2), wild shape (3/day)", "Summon monster V + Chimeric aspect", "Aspect + Third aspect, wild shape (4/day)", "Summon monster VI + Shifter claws increase", "Greater shield ally + Defensive instinct (+3), wild shape (5/day)", "Summon monster VII + Shifter claws increase", "Life bond + Greater chimeric aspect, wild shape (6/day)", "Summon monster VIII + Fourth aspect", "Merge forms + Defensive instinct (+4), wild shape (7/day)", "Summon monster IX + Shifter claws increase", "Greater aspect + Wild shape (8/day)", "Gate + Shifter claws increase", "Twin eidolon + Defensive instinct (+5), final aspect"]}